bleached.py
bleached-1.0.1.dist-info/LICENSE.txt
bleached-1.0.1.dist-info/METADATA
bleached-1.0.1.dist-info/WHEEL
bleached-1.0.1.dist-info/RECORD
